androidssystemfilechooser/__init__.py
androidssystemfilechooser/chooser.py
androidssystemfilechooser/utils.py
AndroidsSystemFileChooser-0.1.0.dist-info/LICENSE
AndroidsSystemFileChooser-0.1.0.dist-info/METADATA
AndroidsSystemFileChooser-0.1.0.dist-info/WHEEL
AndroidsSystemFileChooser-0.1.0.dist-info/top_level.txt
AndroidsSystemFileChooser-0.1.0.dist-info/RECORD
