Metadata-Version: 2.2
Name: AndroidsSystemFileChooser
Version: 0.1.0
Summary: Androids SystemFileChooser with Kivy
Home-page: https://github.com/kuzeyron/AndroidsSystemFileChooser
Author: Mathias Lindström
License: LICENSE
Classifier: Intended Audience :: Developers
Classifier: Topic :: Software Development :: Build Tools
Classifier: Programming Language :: Python :: 3
Requires-Python: >=3.10
License-File: LICENSE
